Metadata-Version: 1.1
Name: openerp-multi-company
Version: 7.0.406
Summary: Multi-Company
Home-page: http://www.openerp.com/
Author: OpenERP SA,SYLEAM
Author-email: TODO
License: AGPL-3
Platform: UNKNOWN
Classifier: Development Status :: 5 - Production/Stable
Classifier: Environment :: Plugins
Classifier: Intended Audience :: Developers
Classifier: License :: OSI Approved :: GNU Affero General Public License v3
Classifier: Natural Language :: English
Classifier: Programming Language :: Python :: 2.7
Classifier: Programming Language :: Python :: Implementation :: CPython
